natureAlgo/__init__.py
natureAlgo/bee_colony.py
natureAlgo-0.1.0.dist-info/LICENSE
natureAlgo-0.1.0.dist-info/METADATA
natureAlgo-0.1.0.dist-info/WHEEL
natureAlgo-0.1.0.dist-info/top_level.txt
natureAlgo-0.1.0.dist-info/RECORD
