Metadata-Version: 2.1
Name: natureAlgo
Version: 0.1.0
Summary: Nature Based Algorithm Library
Home-page: https://natureAlgo.readthedocs.io/
Author: OpenAI's ChatGPT, Shirish Kumar
Author-email: shirishk222@gmail.com
License: MIT
Platform: UNKNOWN
Classifier: Intended Audience :: Developers
Classifier: License :: OSI Approved :: MIT License
Classifier: Programming Language :: Python
Classifier: Programming Language :: Python :: 3.9
Classifier: Programming Language :: Python :: 3.10
Classifier: Operating System :: OS Independent
License-File: LICENSE
